setup.py
g3ar/__init__.py
g3ar/test.py
g3ar.egg-info/PKG-INFO
g3ar.egg-info/SOURCES.txt
g3ar.egg-info/dependency_links.txt
g3ar.egg-info/not-zip-safe
g3ar.egg-info/requires.txt
g3ar.egg-info/top_level.txt
g3ar/decologger/__init__.py
g3ar/decologger/decologger.py
g3ar/decologger/test.py
g3ar/dict_parser/__init__.py
g3ar/dict_parser/dict_parser.py
g3ar/dict_parser/test.py
g3ar/taskbulter/__init__.py
g3ar/taskbulter/exceptions.py
g3ar/taskbulter/process_task.py
g3ar/taskbulter/task_bulter.py
g3ar/taskbulter/utils_class.py
g3ar/threadutils/__init__.py
g3ar/threadutils/contractor.py
g3ar/threadutils/thread_pool.py
g3ar/utils/__init__.py
g3ar/utils/inspect_utils.py
g3ar/utils/ip_calc_utils.py
g3ar/utils/print_utils.py
g3ar/utils/tests.py
g3ar/utils/ipwhois/__init__.py
g3ar/utils/ipwhois/exceptions.py
g3ar/utils/ipwhois/hr.py
g3ar/utils/ipwhois/ipwhois.py
g3ar/utils/ipwhois/net.py
g3ar/utils/ipwhois/nir.py
g3ar/utils/ipwhois/rdap.py
g3ar/utils/ipwhois/utils.py
g3ar/utils/ipwhois/whois.py
g3ar/utils/pyping/__init__.py
g3ar/utils/pyping/isalive.py
g3ar/utils/pyping/ping.py