Metadata-Version: 1.0
Name: g3ar
Version: 0.0.7b2
Summary: Python Coding Toolkit for Pentester.
Home-page: https://github.com/VillanCh/g3ar
Author: v1ll4n/VillanCh
Author-email: v1ll4n@villanch.top
License: BSD 2-Clause License
Platform: UNKNOWN
